LICENSE
MANIFEST.in
README.md
setup.cfg
setup.py
RADWave/__init__.py
RADWave/altiwave.py
RADWave/documentation.py
RADWave/Notebooks/dataset/2010-YASI.csv
RADWave/Notebooks/dataset/IMOSURLs.txt
RADWave/Notebooks/dataset/IMOS_NZ.txt
RADWave/Notebooks/dataset/IMOS_YASI_east.txt
RADWave/Notebooks/dataset/IMOS_YASI_west.txt
RADWave/Notebooks/images/binder.jpg
RADWave/Notebooks/images/illustration.key
RADWave/Notebooks/images/illustration.pdf
RADWave/Notebooks/images/img1.jpg
RADWave/Notebooks/images/img1.pdf
RADWave/Notebooks/images/img2.jpg
RADWave/Notebooks/images/img2.pdf
RADWave/Notebooks/images/img3.jpg
RADWave/Notebooks/images/img4.jpg
RADWave/Notebooks/images/img5.jpg
RADWave/Notebooks/images/img6.jpg
RADWave/Notebooks/images/img7.jpg
RADWave/Notebooks/notebooks/RADWave1-TileAnalysis.ipynb
RADWave/Notebooks/notebooks/RADWave2-ClimateVariability.ipynb
RADWave/Notebooks/notebooks/RADWave3-CycloneYasi.ipynb
RADWave/Notebooks/notebooks/Untitled.ipynb
radwave.egg-info/PKG-INFO
radwave.egg-info/SOURCES.txt
radwave.egg-info/dependency_links.txt
radwave.egg-info/requires.txt
radwave.egg-info/top_level.txt