Metadata-Version: 2.1
Name: radwave
Version: 1.0.8
Summary: A Python interface to perform wave analysis from satellite altimeter data.
Home-page: https://github.com/pyReef-model/RADWave
Author: Tristan Salles
Author-email: tristan.salles@sydney.edu.au
License: UNKNOWN
Platform: UNKNOWN
Classifier: Programming Language :: Python :: 3.5
Classifier: Programming Language :: Python :: 3.6
Classifier: Programming Language :: Python :: 3.7
Classifier: Programming Language :: Python :: 3.8
Classifier: Programming Language :: Python :: 3.9
Requires-Python: >=3.5
